gradio_collection/__init__.py
gradio_collection-1.0.0.dist-info/METADATA
gradio_collection-1.0.0.dist-info/WHEEL
gradio_collection-1.0.0.dist-info/top_level.txt
gradio_collection-1.0.0.dist-info/RECORD
