Metadata-Version: 2.1
Name: gradio_collection
Version: 1.0.0
Summary: A collection of Custom Gradio components.
Home-page: https://github.com/dwancin/gradio-collection/
Author: Daniel Ialcin Misser Westergaard
Keywords: gradio,gradio-custom-component,meta-package
Classifier: Development Status :: 3 - Alpha
Classifier: Intended Audience :: Developers
Classifier: Topic :: Software Development :: Build Tools
Classifier: License :: OSI Approved :: MIT License
Classifier: Programming Language :: Python :: 3
Classifier: Programming Language :: Python :: 3.6
Classifier: Programming Language :: Python :: 3.7
Classifier: Programming Language :: Python :: 3.8
Classifier: Programming Language :: Python :: 3.9
Classifier: Programming Language :: Python :: 3.10
Requires-Python: >=3.6
Requires-Dist: gradio <5.0,>=4.0
Requires-Dist: gradio-toggle
Requires-Dist: gradio-grid
Requires-Dist: gradio-imagefeed
Requires-Dist: gradio-highlightedcode
Requires-Dist: gradio-modal
Requires-Dist: gradio-pdf
Requires-Dist: gradio-calendar
Requires-Dist: gradio-imageslider
Requires-Dist: gradio-folium
Requires-Dist: gradio-notebook
